ovos_translate_plugin_nllb/__init__.py
ovos_translate_plugin_nllb/version.py
ovos_translate_plugin_nllb-0.0.1.dist-info/licenses/LICENSE
ovos_translate_plugin_nllb-0.0.1.dist-info/METADATA
ovos_translate_plugin_nllb-0.0.1.dist-info/WHEEL
ovos_translate_plugin_nllb-0.0.1.dist-info/entry_points.txt
ovos_translate_plugin_nllb-0.0.1.dist-info/top_level.txt
ovos_translate_plugin_nllb-0.0.1.dist-info/RECORD
