Metadata-Version: 2.4
Name: ovos-translate-plugin-nllb
Version: 0.0.1
Summary: OVOS translation module for No Language Left Behind
Home-page: https://github.com/OpenVoiceOS/ovos-translate-plugin-nllb
Author: jarbasAi
Author-email: jarbasai@mailfence.com
License: Apache-2.0
Classifier: Development Status :: 3 - Alpha
Classifier: Intended Audience :: Developers
Classifier: Topic :: Text Processing :: Linguistic
Classifier: License :: OSI Approved :: Apache Software License
Classifier: Programming Language :: Python :: 3.6
Classifier: Programming Language :: Python :: 3.7
Classifier: Programming Language :: Python :: 3.8
Classifier: Programming Language :: Python :: 3.9
Classifier: Programming Language :: Python :: 3.10
Classifier: Programming Language :: Python :: 3.11
License-File: LICENSE
Requires-Dist: ctranslate2
Requires-Dist: sentencepiece
Requires-Dist: ovos-plugin-manager<3.0.0,>=1.0.0
Requires-Dist: huggingface_hub
Provides-Extra: test
Requires-Dist: pytest; extra == "test"
Requires-Dist: pytest-cov; extra == "test"
Dynamic: author
Dynamic: author-email
Dynamic: classifier
Dynamic: home-page
Dynamic: license
Dynamic: license-file
Dynamic: provides-extra
Dynamic: requires-dist
Dynamic: summary
